{
  "indexes": [
    {
      "collectionGroup": "meals",
      "queryScope": "COLLECTION",
      "fields": [
        { "fieldPath": "familyId", "order": "ASCENDING" },
        { "fieldPath": "createdAt", "order": "DESCENDING" }
      ]
    },
    {
      "collectionGroup": "medicines",
      "queryScope": "COLLECTION",
      "fields": [
        { "fieldPath": "familyId", "order": "ASCENDING" },
        { "fieldPath": "createdAt", "order": "DESCENDING" }
      ]
    },
    {
      "collectionGroup": "medicine_checks",
      "queryScope": "COLLECTION",
      "fields": [
        { "fieldPath": "familyId", "order": "ASCENDING" },
        { "fieldPath": "date", "order": "ASCENDING" }
      ]
    },
    {
      "collectionGroup": "medicines",
      "queryScope": "COLLECTION",
      "fields": [
        { "fieldPath": "active", "order": "ASCENDING" },
        { "fieldPath": "reminderHour", "order": "ASCENDING" },
        { "fieldPath": "reminderMinute", "order": "ASCENDING" }
      ]
    }
  ],
  "fieldOverrides": []
}
